latexpp/__init__.py
latexpp/__main__.py
latexpp/_lpp_parsing.py
latexpp/doc/__init__.py
latexpp/fix.py
latexpp/fixes/__init__.py
latexpp/fixes/_newcommand_pylatexenc2.py
latexpp/fixes/_newcommand_pylatexenc3.py
latexpp/fixes/archive.py
latexpp/fixes/bib.py
latexpp/fixes/builtin/__init__.py
latexpp/fixes/builtin/remaining_pragmas.py
latexpp/fixes/builtin/skip.py
latexpp/fixes/comments.py
latexpp/fixes/deps.py
latexpp/fixes/environment_contents.py
latexpp/fixes/figures.py
latexpp/fixes/ifsimple.py
latexpp/fixes/input.py
latexpp/fixes/labels.py
latexpp/fixes/macro_subst.py
latexpp/fixes/newcommand.py
latexpp/fixes/pkg/__init__.py
latexpp/fixes/pkg/cleveref.py
latexpp/fixes/pkg/phfparen.py
latexpp/fixes/pkg/phfqit.py
latexpp/fixes/pkg/phfthm.py
latexpp/fixes/preamble.py
latexpp/fixes/ref.py
latexpp/fixes/regional_fix.py
latexpp/fixes/usepackage.py
latexpp/macro_subst_helper.py
latexpp/pragma_fix.py
latexpp/preprocessor.py
latexpp-0.2.0a1.dist-info/METADATA
latexpp-0.2.0a1.dist-info/WHEEL
latexpp-0.2.0a1.dist-info/RECORD
