Metadata-Version: 2.1
Name: latexpp
Version: 0.2.0a1
Summary: Latex preprocessor — apply macro definitions, remove comments, and more
License: MIT
Author: Philippe Faist
Requires-Python: >=3.7,<4.0
Classifier: License :: OSI Approved :: MIT License
Classifier: Programming Language :: Python :: 3
Classifier: Programming Language :: Python :: 3.7
Classifier: Programming Language :: Python :: 3.8
Classifier: Programming Language :: Python :: 3.9
Classifier: Programming Language :: Python :: 3.10
Classifier: Programming Language :: Python :: 3.11
Requires-Dist: PyYAML (>=6.0,<7.0)
Requires-Dist: colorlog (>=6.0.0a4)
Requires-Dist: pylatexenc (>=3.0a15)
